---
title: Java中Enum类型的序列化
layout: post
permalink: /2012/06/Java中Enum类型的序列化/
date: Fri Jun 15 21:31:14 CST 2012
published: true
pygments: true
---

在Java中，对Enum类型的序列化与其他对象类型的序列化有所不同，今天就来看看到底有什么不同。下面先来看下在Java中，我们定义的Enum在被编译之后是长成什么样子的。

Java代码：

{% highlight java linenos %}
	public enum FruitEnum {
		APPLE, ORAGE
	}

{% endhighlight %}


上面的代码定义了一个FruitEnum类型，是最简单形式的，下面我们来看看编译之后的字节码。

字节码：

{% highlight java linenos %}
	public final class com.taobao.tianxiao.FruitEnum extends java.lang.Enum
	....
	....
	....
	{
	public static final com.taobao.tianxiao.FruitEnum APPLE;
	
	public static final com.taobao.tianxiao.FruitEnum ORAGE;
	
	static {};
	  Code:
	   Stack=4, Locals=0, Args_size=0
	   0:	new	#1; //class com/taobao/tianxiao/FruitEnum
	   3:	dup
	   4:	ldc	#13; //String APPLE
	   6:	iconst_0
	   7:	invokespecial	#14; //Method "&lt;init&gt;":(Ljava/lang/String;I)V
	   10:	putstatic	#18; //Field APPLE:Lcom/taobao/tianxiao/FruitEnum;
	   13:	new	#1; //class com/taobao/tianxiao/FruitEnum
	   16:	dup
	   17:	ldc	#20; //String ORAGE
	   19:	iconst_1
	   20:	invokespecial	#14; //Method "&lt;init&gt;":(Ljava/lang/String;I)V
	   23:	putstatic	#21; //Field ORAGE:Lcom/taobao/tianxiao/FruitEnum;
	   26:	iconst_2
	   27:	anewarray	#1; //class com/taobao/tianxiao/FruitEnum
	   30:	dup
	   31:	iconst_0
	   32:	getstatic	#18; //Field APPLE:Lcom/taobao/tianxiao/FruitEnum;
	   35:	aastore
	   36:	dup
	   37:	iconst_1
	   38:	getstatic	#21; //Field ORAGE:Lcom/taobao/tianxiao/FruitEnum;
	   41:	aastore
	   42:	putstatic	#23; //Field ENUM$VALUES:[Lcom/taobao/tianxiao/FruitEnum;
	   45:	return
	  LineNumberTable: 
	   line 4: 0
	   line 3: 26
	
	public static com.taobao.tianxiao.FruitEnum[] values();
	  Code:
	   Stack=5, Locals=3, Args_size=0
	   0:	getstatic	#23; //Field ENUM$VALUES:[Lcom/taobao/tianxiao/FruitEnum;
	   3:	dup
	   4:	astore_0
	   5:	iconst_0
	   6:	aload_0
	   7:	arraylength
	   8:	dup
	   9:	istore_1
	   10:	anewarray	#1; //class com/taobao/tianxiao/FruitEnum
	   13:	dup
	   14:	astore_2
	   15:	iconst_0
	   16:	iload_1
	   17:	invokestatic	#31; //Method java/lang/System.arraycopy:(Ljava/lang/Object;ILjava/lang/Object;II)V
	   20:	aload_2
	   21:	areturn
	  LineNumberTable: 
	   line 1: 0
	
	public static com.taobao.tianxiao.FruitEnum valueOf(java.lang.String);
	  Code:
	   Stack=2, Locals=1, Args_size=1
	   0:	ldc	#1; //class com/taobao/tianxiao/FruitEnum
	   2:	aload_0
	   3:	invokestatic	#39; //Method java/lang/Enum.valueOf:(Ljava/lang/Class;Ljava/lang/String;)Ljava/lang/Enum;
	   6:	checkcast	#1; //class com/taobao/tianxiao/FruitEnum
	   9:	areturn
	  LineNumberTable: 
	   line 1: 0
	}

{% endhighlight %}


上面的字节码已经去掉的常量池部分，但是即便如此，在我们的源代码中如此简单的一个FruitEnum类，编译器居然为我们产生了这么多的字节码，哇哦～～～～～～～～

仔细地看这段代码， 编译器是在为我们创建一个类，这个类继承自 java.lang.Enum ，有两个公共的、静态的、被声明成final的属性，它们的类型就是我们定义的FruitEnum。同时，编译器还生成了一个静态初始话器，就是字节码中static{};这一行下面的代码，其中的字节码创建了两个FruitEnum对象，同时分别赋值给APPLE和ORANGE这两个属性，调用的构造函数是定义在 java.lang.Enum中的protected Enum(String name, int ordinal)方法。在创建完成两个FruitEnum对象并且分别赋值给APPLE和ORIGIN之后，还创建了一个名叫ENUM$VALUES的数组，然后把APPLE和ORIGIN按照定义的顺��放如这个数组中。

除了这个静态初始化器之外，编译器还为我们生成了两个静态方法，values()和 valueOf(java.lang.String)方法。其中values()方法将ENUM$VALUES数组拷贝一份然后返回，而valueOf(java.lang.String)方法则会调用java.lang.Enum类中的valueOf方法，其作用是根据参数名找到对应的具体的枚举对象，如果找不到的话会抛出一个IllegalArgumentException异常。

从上面的叙述可以看到，我们定义的枚举类型，经过编译器的处理最终会编程一个对象的定义，其中的枚举变量其实就是类的静态变量，因此Java中的枚举类型其实是具有很多对象的特性的，只不过平时我们都不太用到，比如枚举可以实现接口(不能继承)、定义方法等等。为了保证枚举类型像Java规范中所说的那样，每一个枚举类型极其定义的枚举变量在JVM中都是唯一的，在枚举类型的序列化和反序列化上，Java做了特殊的规定。原文如下(摘自Java的序列化规范)：

<div class="quote_title">引用</div>
<div class="quote_div"><br />Enum constants are serialized differently than ordinary serializable or externalizable objects. The serialized form of an enum constant consists solely of its name; field values of the constant are not present in the form. To serialize an enum constant, ObjectOutputStream writes the value returned by the enum constant's name method. To deserialize an enum constant, ObjectInputStream reads the constant name from the stream; the deserialized constant is then obtained by calling the java.lang.Enum.valueOf method, passing the constant's enum type along with the received constant name as arguments. Like other serializable or externalizable objects, enum constants can function as the targets of back references appearing subsequently in the serialization stream.<br />The process by which enum constants are serialized cannot be customized: any class-specific writeObject, readObject, readObjectNoData, writeReplace, and readResolve methods defined by enum types are ignored during serialization and deserialization. Similarly, any serialPersistentFields or serialVersionUID field declarations are also ignored--all enum types have a fixedserialVersionUID of 0L. Documenting serializable fields and data for enum types is unnecessary, since there is no variation in the type of data sent.<br /></div>


大概意思就是说，在序列化的时候Java仅仅是将枚举对象的name属性输出到结果中，反序列化的时候则是通过java.lang.Enum的valueOf方法来根据名字查找枚举对象。同时，编译器是不允许任何对这种序列化机制的定制的，因此禁用了writeObject、readObject、readObjectNoData、writeReplace和readResolve等方法。下面我们来��看反序列化时候被调用的那个valueOf方法长什么样子。

java代码：

{% highlight java linenos %}
	public static &lt;T extends Enum&lt;T&gt;&gt; T valueOf(Class&lt;T&gt; enumType,
	                                                String name) {
	        T result = enumType.enumConstantDirectory().get(name);
	        if (result != null)
	            return result;
	        if (name == null)
	            throw new NullPointerException("Name is null");
	        throw new IllegalArgumentException(
	            "No enum const " + enumType +"." + name);
	    }

{% endhighlight %}


从代码中可以看到，代码会尝试从调用enumType这个Class对象的enumConstantDirectory()方法返回的map中获取名字为name的枚举对象，如果不存在就会抛出异常。再进一步跟到enumConstantDirectory()方法，就会发现到最后会以反射的方式调用enumType这个类型的values()静态方法，也就是上面我们看到的编译器为我们创建的那个方法，然后用返回结果填充enumType这个Class对象中的enumConstantDirectory属性。

在了解了Java如何处理枚举的定义以及序列化和反序列化枚举类型之后，我们就需要在系统或者类库升级时，对其中定义的枚举类型多加注意，为了保持代码上的兼容性，如果我们定义的枚举类型有可能会被序列化保存(放到文件中、保存到��据库中，进入分布式内存缓存中)，那么我们是不能够删除原来枚举类型中定义的任何枚举对象的，否则程序在运行过程中，JVM就会抱怨找不到与某个名字对应的枚举对象了。另外，在远程方法调用过程中，如果我们发布的客户端接口返回值中使用了枚举类型，那么服务端在升级过程中就需要特别注意。如果在接口的返回结果的枚举类型中添加了新的枚举值，那就会导致仍然在使用老的客户端的那些应用出现调用失败的情况。因此，针对以上两种情况，应该尽量避免使用枚举，如果实在要用，也需要仔细设计，因为一旦用了枚举，有可能会给后期维护带来隐患。
